README.md
setup.py
bettertime/__init__.py
bettertime/exceptions.py
bettertime/formatter.py
bettertime/lexer.py
bettertime/parser.py
bettertime/regex.py
bettertime.egg-info/PKG-INFO
bettertime.egg-info/SOURCES.txt
bettertime.egg-info/dependency_links.txt
bettertime.egg-info/not-zip-safe
bettertime.egg-info/top_level.txt