Metadata-Version: 2.1
Name: bettertime
Version: 1.0.0
Summary: Library converting string date expressions to seconds [int].
Home-page: https://github.com/DarkJoij/bettertime
Author: Dallas
License: MIT License
Platform: UNKNOWN
